src/ADC128S102_Driver.v
// ADC128S102_Driver.v
module ADC128S102_Driver (
    input       clk,
    input       rst_n,
    input [2:0] Addr,     //选择线
    input       Conv_go,  //数据从用户输入到驱动使能信号
    input       dout,     //由ADC芯片 输入到本驱动 

    output reg [11:0] data,       //输出11位数据给用户
    output reg        conv_done,  //数据输出信号
    output reg        cs_n,
    output reg        sclk,
    output reg        din         //地址选择
);

    parameter CLOCK_FREQ = 50_000_000;  //50Mhz
    parameter SRCLK_FREQ = 12_500_000;  //12.5Mhz
    parameter MCNT_DIV = CLOCK_FREQ / (SRCLK_FREQ * 2) - 1;

    reg [29:0] div_cnt;
    reg [11:0] r_data;
    reg [ 2:0] r_Addr;
    reg        en;  //使能信号
    //分频计数器 实现12.5Mhz下的最小时间单位 40ns
    always @(posedge clk or negedge rst_n) begin
        if (~rst_n) begin
            div_cnt <= 0;
        end
        else if (div_cnt == MCNT_DIV) begin
            div_cnt <= 0;
        end
        else begin
            div_cnt <= div_cnt + 1'd1;
        end
    end

    reg [5:0] count;
    always @(posedge clk or negedge rst_n) begin
        if (~rst_n) begin
            count <= 6'd0;
        end
        else if ((div_cnt == MCNT_DIV) && (en)) begin
            if (count == 6'd34) begin
                count <= 6'd0;
            end
            else begin
                count <= count + 1'd1;
            end
        end
    end

    //en生产信号
    always @(posedge clk or negedge rst_n) begin
        if (~rst_n) begin
            en <= 0;
        end
        else if (Conv_go) begin
            en <= 1;
        end
        else if ((count == 34) && (div_cnt == MCNT_DIV)) begin
            en <= 0;
        end
        else begin
            en <= en;
        end
    end

    //暂存addr值 防止addr不稳定
    always @(posedge clk or negedge rst_n) begin
        if (~rst_n) begin
            r_Addr <= 0;
        end
        else begin
            r_Addr <= Addr;
        end
    end

    always @(posedge clk or negedge rst_n) begin
        if (~rst_n) begin
            sclk      <= 0;
            conv_done <= 0;
            din       <= 0;
            r_data    <= 12'd0;
        end
        else if (div_cnt == MCNT_DIV) begin
            case (count)
                0: begin
                    sclk <= 1;
                    cs_n <= 1;
                end
                1: cs_n <= 0;
                2: sclk <= 0;
                3: sclk <= 1;
                4: sclk <= 0;
                5: sclk <= 1;
                6: begin
                    sclk <= 0;
                    din  <= r_Addr[2];
                end
                7: sclk <= 1;
                8: begin
                    sclk <= 0;
                    din  <= r_Addr[1];
                end
                9: sclk <= 1;
                10: begin
                    sclk <= 0;
                    din  <= r_Addr[0];
                end

                11: begin
                    sclk       <= 1;
                    r_data[11] <= dout;
                end
                12:      sclk <= 0;
                13: begin
                    sclk       <= 1;
                    r_data[10] <= dout;
                end
                14:      sclk <= 0;
                15: begin
                    sclk      <= 1;
                    r_data[9] <= dout;
                end
                16:      sclk <= 0;
                17: begin
                    sclk      <= 1;
                    r_data[8] <= dout;
                end
                18:      sclk <= 0;
                19: begin
                    sclk      <= 1;
                    r_data[7] <= dout;
                end
                20:      sclk <= 0;
                21: begin
                    sclk      <= 1;
                    r_data[6] <= dout;
                end
                22:      sclk <= 0;
                23: begin
                    sclk      <= 1;
                    r_data[5] <= dout;
                end
                24:      sclk <= 0;
                25: begin
                    sclk      <= 1;
                    r_data[4] <= dout;
                end
                26:      sclk <= 0;
                27: begin
                    sclk      <= 1;
                    r_data[3] <= dout;
                end
                28:      sclk <= 0;
                29: begin
                    sclk      <= 1;
                    r_data[2] <= dout;
                end
                30:      sclk <= 0;
                31: begin
                    sclk      <= 1;
                    r_data[1] <= dout;
                end
                32:      sclk <= 0;
                33: begin
                    sclk      <= 1;
                    r_data[0] <= dout;
                end
                34: begin
                    cs_n <= 1;
                end
                default: sclk <= 1;
            endcase
        end
    end

    always @(posedge clk or negedge rst_n) begin
        if (~rst_n) begin
            data      <= 0;
            conv_done <= 0;
        end
        else if ((count == 34) && (div_cnt == MCNT_DIV)) begin
            data      <= r_data;
            conv_done <= 1;
        end
        else begin
            data      <= 0;
            conv_done <= 0;
        end
    end



endmodule

src/ADC128S102_Driver_tb.v
// ADC128S102_Driver_tb.v
`timescale 1ns / 1ps
module ADC128S102_Driver_tb;
    reg         clk = 1;
    reg         rst_n;
    reg  [ 2:0] Addr;  //选择线
    reg         Conv_go;  //数据从用户输入到驱动使能信号
    reg         dout;  //由ADC芯片 输入到本驱动 

    wire [11:0] data;  //输出11位数据给用户
    wire        conv_done;  //数据输出信号
    wire        cs_n;
    wire        sclk;
    wire        din;

    always #10 clk = ~clk;

    initial begin
        $dumpfile("wave.vcd");
        $dumpvars(0, ADC128S102_Driver_tb);
    end

    initial begin
        rst_n   = 0;
        Conv_go = 0;
        Addr    = 0;
        #101;
        rst_n = 1;
        #100;
        Conv_go = 1;
        Addr    = 3;
        #20;
        Conv_go = 0;
        wait(!cs_n);
        @(negedge sclk);
        dout=0;//DB15
        @(negedge sclk);
        dout=0;//DB14
        @(negedge sclk);
        dout=0;//DB13
        @(negedge sclk);
        dout=0;//DB12
        @(negedge sclk);
        dout=1;//DB11
        @(negedge sclk);
        dout=0;//DB10
        @(negedge sclk);
        dout=1;//DB9
        @(negedge sclk);
        dout=0;//DB8
        @(negedge sclk);
        dout=1;//DB7
        @(negedge sclk);
        dout=0;//DB6
        @(negedge sclk);
        dout=1;//DB5
        @(negedge sclk);
        dout=0;//DB4
        @(negedge sclk);
        dout=1;//DB3
        @(negedge sclk);
        dout=0;//DB2
        @(negedge sclk);
        dout=1;//DB1
        @(negedge sclk);
        dout=0;//DB0
        #100;
        $finish;
    end

    ADC128S102_Driver u_ADC128S102_Driver (
        .clk      (clk),
        .rst_n    (rst_n),
        .Addr     (Addr),
        .Conv_go  (Conv_go),
        .dout     (dout),
        .data     (data),
        .conv_done(conv_done),
        .cs_n     (cs_n),
        .sclk     (sclk),
        .din      (din)
    );


endmodule

wave.vcd
$date
	Mon May 12 18:45:12 2025
$end
$version
	Icarus Verilog
$end
$timescale
	1ps
$end
$scope module ADC128S102_Driver_tb $end
$var wire 1 ! sclk $end
$var wire 1 " din $end
$var wire 12 # data [11:0] $end
$var wire 1 $ cs_n $end
$var wire 1 % conv_done $end
$var reg 3 & Addr [2:0] $end
$var reg 1 ' Conv_go $end
$var reg 1 ( clk $end
$var reg 1 ) dout $end
$var reg 1 * rst_n $end
$scope module u_ADC128S102_Driver $end
$var wire 3 + Addr [2:0] $end
$var wire 1 ' Conv_go $end
$var wire 1 ( clk $end
$var wire 1 ) dout $end
$var wire 1 * rst_n $end
$var reg 1 % conv_done $end
$var reg 6 , count [5:0] $end
$var reg 1 $ cs_n $end
$var reg 12 - data [11:0] $end
$var reg 1 " din $end
$var reg 30 . div_cnt [29:0] $end
$var reg 1 / en $end
$var reg 3 0 r_Addr [2:0] $end
$var reg 12 1 r_data [11:0] $end
$var reg 1 ! sclk $end
$upscope $end
$upscope $end
$enddefinitions $end
#0
$dumpvars
bx 1
b0 0
0/
b0 .
b0 -
b0 ,
b0 +
0*
x)
1(
0'
b0 &
0%
x$
b0 #
0"
0!
$end
#10000
0(
#20000
1(
#30000
0(
#40000
1(
#50000
0(
#60000
1(
#70000
0(
#80000
1(
#90000
0(
#100000
1(
#101000
1*
#110000
0(
#120000
b1 .
1(
#130000
0(
#140000
1$
1!
b0 .
1(
#150000
0(
#160000
b1 .
1(
#170000
0(
#180000
b0 .
1(
#190000
0(
#200000
b1 .
1(
#201000
b11 &
b11 +
1'
#210000
0(
#220000
b11 0
1/
b0 .
1(
#221000
0'
#230000
0(
#240000
b1 .
1(
#250000
0(
#260000
b1 ,
b0 .
1(
#270000
0(
#280000
b1 .
1(
#290000
0(
#300000
0$
b10 ,
b0 .
1(
#310000
0(
#320000
b1 .
1(
#330000
0(
#340000
0)
0!
b11 ,
b0 .
1(
#350000
0(
#360000
b1 .
1(
#370000
0(
#380000
1!
b100 ,
b0 .
1(
#390000
0(
#400000
b1 .
1(
#410000
0(
#420000
0!
b101 ,
b0 .
1(
#430000
0(
#440000
b1 .
1(
#450000
0(
#460000
1!
b110 ,
b0 .
1(
#470000
0(
#480000
b1 .
1(
#490000
0(
#500000
0!
b111 ,
b0 .
1(
#510000
0(
#520000
b1 .
1(
#530000
0(
#540000
1!
b1000 ,
b0 .
1(
#550000
0(
#560000
b1 .
1(
#570000
0(
#580000
1"
0!
b1001 ,
b0 .
1(
#590000
0(
#600000
b1 .
1(
#610000
0(
#620000
1!
b1010 ,
b0 .
1(
#630000
0(
#640000
b1 .
1(
#650000
0(
#660000
1)
0!
b1011 ,
b0 .
1(
#670000
0(
#680000
b1 .
1(
#690000
0(
#700000
b1xxxxxxxxxxx 1
1!
b1100 ,
b0 .
1(
#710000
0(
#720000
b1 .
1(
#730000
0(
#740000
0)
0!
b1101 ,
b0 .
1(
#750000
0(
#760000
b1 .
1(
#770000
0(
#780000
b10xxxxxxxxxx 1
1!
b1110 ,
b0 .
1(
#790000
0(
#800000
b1 .
1(
#810000
0(
#820000
1)
0!
b1111 ,
b0 .
1(
#830000
0(
#840000
b1 .
1(
#850000
0(
#860000
b101xxxxxxxxx 1
1!
b10000 ,
b0 .
1(
#870000
0(
#880000
b1 .
1(
#890000
0(
#900000
0)
0!
b10001 ,
b0 .
1(
#910000
0(
#920000
b1 .
1(
#930000
0(
#940000
b1010xxxxxxxx 1
1!
b10010 ,
b0 .
1(
#950000
0(
#960000
b1 .
1(
#970000
0(
#980000
1)
0!
b10011 ,
b0 .
1(
#990000
0(
#1000000
b1 .
1(
#1010000
0(
#1020000
b10101xxxxxxx 1
1!
b10100 ,
b0 .
1(
#1030000
0(
#1040000
b1 .
1(
#1050000
0(
#1060000
0)
0!
b10101 ,
b0 .
1(
#1070000
0(
#1080000
b1 .
1(
#1090000
0(
#1100000
b101010xxxxxx 1
1!
b10110 ,
b0 .
1(
#1110000
0(
#1120000
b1 .
1(
#1130000
0(
#1140000
1)
0!
b10111 ,
b0 .
1(
#1150000
0(
#1160000
b1 .
1(
#1170000
0(
#1180000
b1010101xxxxx 1
1!
b11000 ,
b0 .
1(
#1190000
0(
#1200000
b1 .
1(
#1210000
0(
#1220000
0)
0!
b11001 ,
b0 .
1(
#1230000
0(
#1240000
b1 .
1(
#1250000
0(
#1260000
b10101010xxxx 1
1!
b11010 ,
b0 .
1(
#1270000
0(
#1280000
b1 .
1(
#1290000
0(
#1300000
1)
0!
b11011 ,
b0 .
1(
#1310000
0(
#1320000
b1 .
1(
#1330000
0(
#1340000
b101010101xxx 1
1!
b11100 ,
b0 .
1(
#1350000
0(
#1360000
b1 .
1(
#1370000
0(
#1380000
0)
0!
b11101 ,
b0 .
1(
#1390000
0(
#1400000
b1 .
1(
#1410000
0(
#1420000
b1010101010xx 1
1!
b11110 ,
b0 .
1(
#1430000
0(
#1440000
b1 .
1(
#1450000
0(
#1460000
1)
0!
b11111 ,
b0 .
1(
#1470000
0(
#1480000
b1 .
1(
#1490000
0(
#1500000
b10101010101x 1
1!
b100000 ,
b0 .
1(
#1510000
0(
#1520000
b1 .
1(
#1530000
0(
#1540000
0)
0!
b100001 ,
b0 .
1(
#1550000
0(
#1560000
b1 .
1(
#1570000
0(
#1580000
b101010101010 1
1!
b100010 ,
b0 .
1(
#1590000
0(
#1600000
b1 .
1(
#1610000
0(
#1620000
1%
b101010101010 #
b101010101010 -
1$
0/
b0 ,
b0 .
1(
#1630000
0(
#1640000
b1 .
0%
b0 #
b0 -
1(
